{"name":HypnotizdCam,"stats":{{""name"":"minecraft.custom.time_since_rest",""amount"":28126,"rank":31,"GWR":1,"percentage":0.02602529781829242},{""name"":"minecraft.custom.time_since_death",""amount"":28126,"rank":36,"GWR":2,"percentage":0.02394473535329416},{""name"":"minecraft.custom.jump",""amount"":1,"rank":44,"GWR":3,"percentage":8.552542114855509e-06},{""name"":"minecraft.custom.fly_one_cm",""amount"":119235,"rank":53,"GWR":4,"percentage":0.004777591252822351},{""name"":"minecraft.custom.leave_game",""amount"":1,"rank":54,"GWR":5,"percentage":0.0029515067441929104},{""name"":"minecraft.custom.sneak_time",""amount"":84,"rank":54,"GWR":6,"percentage":6.926123999024603e-05},{""name"":"minecraft.custom.total_world_time",""amount"":28126,"rank":55,"GWR":7,"percentage":0.0012633348925902533},{""name"":"minecraft.custom.play_time",""amount"":28126,"rank":55,"GWR":8,"percentage":0.0012633348925902533}}}