[{"name":"Renthedog","amount":29654},{"name":"cubfan135","amount":15626},{"name":"GoodTimeWithScar","amount":10133},{"name":"iJevin","amount":4285},{"name":"Etho","amount":2754},{"name":"Tango","amount":1743},{"name":"Zedaph","amount":1286},{"name":"iskall85","amount":878},{"name":"Docm77","amount":851},{"name":"MythicalSausage","amount":678},{"name":"RentheKing","amount":505},{"name":"Grian","amount":430},{"name":"falsesymmetry","amount":363},{"name":"joehillssays","amount":342},{"name":"xBCrafted","amount":305},{"name":"Stressmonster101","amount":236},{"name":"Xisuma","amount":168},{"name":"PearlescentMoon","amount":143},{"name":"impulseSV","amount":93},{"name":"GeminiTay","amount":44},{"name":"hypnotizd","amount":44},{"name":"BdoubleO100","amount":38},{"name":"Smajor1995","amount":32},{"name":"VintageBeef","amount":26},{"name":"Keralis1","amount":9},{"name":"Smallishbeans","amount":8},{"name":"ZombieCleo","amount":4}]