[{"name":"iJevin","amount":2721},{"name":"impulseSV","amount":2498},{"name":"falsesymmetry","amount":1341},{"name":"Xisuma","amount":354},{"name":"Docm77","amount":344},{"name":"cubfan135","amount":311},{"name":"PearlescentMoon","amount":256},{"name":"Mumbo","amount":195},{"name":"GoodTimeWithScar","amount":77},{"name":"Renthedog","amount":64},{"name":"Tango","amount":32},{"name":"VintageBeef","amount":15},{"name":"xBCrafted","amount":8},{"name":"Etho","amount":8},{"name":"ZombieCleo","amount":8},{"name":"Keralis1","amount":1},{"name":"Zedaph","amount":1}]