[{"name":"Tango","amount":910},{"name":"Keralis1","amount":771},{"name":"falsesymmetry","amount":315},{"name":"impulseSV","amount":254},{"name":"Grian","amount":216},{"name":"cubfan135","amount":176},{"name":"GoodTimeWithScar","amount":174},{"name":"iJevin","amount":161},{"name":"hypnotizd","amount":160},{"name":"Renthedog","amount":157},{"name":"ZombieCleo","amount":96},{"name":"BdoubleO100","amount":41},{"name":"Zedaph","amount":39},{"name":"Docm77","amount":26},{"name":"Etho","amount":10},{"name":"Xisuma","amount":9},{"name":"VintageBeef","amount":6},{"name":"joehillssays","amount":6},{"name":"GeminiTay","amount":2},{"name":"Mumbo","amount":1}]