[{"name":"xBCrafted","amount":106},{"name":"Renthedog","amount":90},{"name":"Docm77","amount":71},{"name":"cubfan135","amount":66},{"name":"hypnotizd","amount":61},{"name":"RentheKing","amount":45},{"name":"Stressmonster101","amount":35},{"name":"falsesymmetry","amount":21},{"name":"iskall85","amount":13},{"name":"Xisuma","amount":9},{"name":"MythicalSausage","amount":7},{"name":"VintageBeef","amount":5},{"name":"ZombieCleo","amount":3},{"name":"fWhip","amount":3},{"name":"Zedaph","amount":3},{"name":"Tango","amount":2},{"name":"BdoubleO100","amount":1},{"name":"GoodTimeWithScar","amount":1}]