[{"name":"falsesymmetry","amount":4804},{"name":"Keralis1","amount":2472},{"name":"iJevin","amount":1286},{"name":"Grian","amount":737},{"name":"Tango","amount":633},{"name":"GoodTimeWithScar","amount":328},{"name":"joehillssays","amount":268},{"name":"PearlescentMoon","amount":263},{"name":"Xisuma","amount":153},{"name":"cubfan135","amount":69},{"name":"iskall85","amount":68},{"name":"Docm77","amount":46},{"name":"Renthedog","amount":44},{"name":"Zedaph","amount":36},{"name":"hypnotizd","amount":31},{"name":"MythicalSausage","amount":16},{"name":"Stressmonster101","amount":16},{"name":"ZombieCleo","amount":15},{"name":"Smallishbeans","amount":12},{"name":"Mumbo","amount":4},{"name":"impulseSV","amount":4},{"name":"Etho","amount":1}]