[{"name":"iJevin","amount":610},{"name":"BdoubleO100","amount":271},{"name":"impulseSV","amount":160},{"name":"Tango","amount":156},{"name":"cubfan135","amount":67},{"name":"Keralis1","amount":48},{"name":"Renthedog","amount":37},{"name":"falsesymmetry","amount":35},{"name":"Docm77","amount":18},{"name":"Xisuma","amount":11},{"name":"iskall85","amount":10},{"name":"xBCrafted","amount":8},{"name":"Etho","amount":5},{"name":"GoodTimeWithScar","amount":5},{"name":"Grian","amount":3},{"name":"hypnotizd","amount":1}]