[{"name":"Zedaph","amount":94},{"name":"Xisuma","amount":62},{"name":"Grian","amount":55},{"name":"Keralis1","amount":38},{"name":"iJevin","amount":35},{"name":"xBCrafted","amount":21},{"name":"VintageBeef","amount":16},{"name":"falsesymmetry","amount":13},{"name":"BdoubleO100","amount":12},{"name":"cubfan135","amount":11},{"name":"GoodTimeWithScar","amount":11},{"name":"Docm77","amount":10},{"name":"Tango","amount":5},{"name":"Etho","amount":4},{"name":"Renthedog","amount":3},{"name":"OrionSound","amount":2},{"name":"PearlescentMoon","amount":2},{"name":"Mumbo","amount":2},{"name":"RentheKing","amount":2},{"name":"impulseSV","amount":2},{"name":"GeminiTay","amount":1},{"name":"iskall85","amount":1},{"name":"ZombieCleo","amount":1},{"name":"fWhip","amount":1},{"name":"ShubbleYT","amount":1}]