[{"name":"iJevin","amount":296444},{"name":"impulseSV","amount":58233},{"name":"falsesymmetry","amount":5958},{"name":"GoodTimeWithScar","amount":2560},{"name":"Tango","amount":2401},{"name":"Grian","amount":2294},{"name":"Keralis1","amount":1967},{"name":"cubfan135","amount":1578},{"name":"hypnotizd","amount":1464},{"name":"joehillssays","amount":1290},{"name":"Docm77","amount":1062},{"name":"Renthedog","amount":1022},{"name":"PearlescentMoon","amount":931},{"name":"ZombieCleo","amount":770},{"name":"RentheKing","amount":682},{"name":"xBCrafted","amount":628},{"name":"GeminiTay","amount":549},{"name":"Xisuma","amount":539},{"name":"BdoubleO100","amount":359},{"name":"Zedaph","amount":333},{"name":"Etho","amount":325},{"name":"iskall85","amount":259},{"name":"Minerva246","amount":252},{"name":"Stressmonster101","amount":229},{"name":"Smallishbeans","amount":228},{"name":"MythicalSausage","amount":219},{"name":"OrionSound","amount":211},{"name":"SolidarityGaming","amount":174},{"name":"VintageBeef","amount":96},{"name":"ShubbleYT","amount":79},{"name":"Smajor1995","amount":73},{"name":"Mumbo","amount":73},{"name":"Skizzleman","amount":65},{"name":"Welsknight","amount":64},{"name":"LDShadowLady","amount":61},{"name":"Pixlriffs","amount":51},{"name":"Firecracker1195","amount":18},{"name":"Watcher_Grian","amount":3},{"name":"HBomb94","amount":1}]