[{"name":"Docm77","amount":52124},{"name":"GeminiTay","amount":8545},{"name":"GoodTimeWithScar","amount":5936},{"name":"Keralis1","amount":2811},{"name":"Xisuma","amount":2751},{"name":"VintageBeef","amount":950},{"name":"Welsknight","amount":565},{"name":"PearlescentMoon","amount":371},{"name":"cubfan135","amount":313},{"name":"Etho","amount":273},{"name":"impulseSV","amount":200},{"name":"ZombieCleo","amount":186},{"name":"BdoubleO100","amount":183},{"name":"xBCrafted","amount":118},{"name":"Grian","amount":83},{"name":"Smallishbeans","amount":35},{"name":"MythicalSausage","amount":21}]