[{"name":"Tango","amount":3124},{"name":"GoodTimeWithScar","amount":1993},{"name":"Docm77","amount":1420},{"name":"iJevin","amount":1327},{"name":"joehillssays","amount":963},{"name":"impulseSV","amount":947},{"name":"xBCrafted","amount":854},{"name":"Grian","amount":824},{"name":"PearlescentMoon","amount":624},{"name":"cubfan135","amount":622},{"name":"ZombieCleo","amount":556},{"name":"falsesymmetry","amount":494},{"name":"hypnotizd","amount":487},{"name":"BdoubleO100","amount":447},{"name":"Stressmonster101","amount":382},{"name":"Renthedog","amount":379},{"name":"Keralis1","amount":365},{"name":"Etho","amount":363},{"name":"Zedaph","amount":280},{"name":"Xisuma","amount":226},{"name":"RentheKing","amount":203},{"name":"iskall85","amount":175},{"name":"GeminiTay","amount":93},{"name":"VintageBeef","amount":76},{"name":"MythicalSausage","amount":69},{"name":"Welsknight","amount":46},{"name":"Mumbo","amount":36},{"name":"Smallishbeans","amount":18},{"name":"Pixlriffs","amount":15},{"name":"MumboJumbo","amount":7},{"name":"OrionSound","amount":1},{"name":"STEAKFG","amount":1},{"name":"SolidarityGaming","amount":1}]