[{"name":"Etho","amount":233},{"name":"RentheKing","amount":146},{"name":"GeminiTay","amount":56},{"name":"Docm77","amount":48},{"name":"Renthedog","amount":43},{"name":"xBCrafted","amount":40},{"name":"impulseSV","amount":37},{"name":"iJevin","amount":34},{"name":"joehillssays","amount":20},{"name":"falsesymmetry","amount":14},{"name":"MythicalSausage","amount":9},{"name":"Tango","amount":4},{"name":"Keralis1","amount":2},{"name":"Grian","amount":1},{"name":"PearlescentMoon","amount":1},{"name":"cubfan135","amount":1}]