[{"name":"falsesymmetry","amount":67},{"name":"Xisuma","amount":55},{"name":"Tango","amount":43},{"name":"impulseSV","amount":28},{"name":"xBCrafted","amount":15},{"name":"Biffa2001","amount":15},{"name":"topmass","amount":9},{"name":"iJevin","amount":7},{"name":"monkeyfarm","amount":6},{"name":"PythonGB","amount":5},{"name":"Mumbo","amount":4},{"name":"Spumwackles","amount":4},{"name":"Etho","amount":3},{"name":"hypnotizd","amount":3},{"name":"KingDaddyDMAC","amount":2},{"name":"zueljin","amount":2},{"name":"ZombieCleo","amount":2},{"name":"Tinfoilchef","amount":2}]