[{"name":"Xisuma","amount":1200},{"name":"Mumbo","amount":707},{"name":"falsesymmetry","amount":523},{"name":"Tango","amount":467},{"name":"xBCrafted","amount":332},{"name":"zueljin","amount":251},{"name":"sl1pg8r","amount":248},{"name":"impulseSV","amount":221},{"name":"KingDaddyDMAC","amount":189},{"name":"topmass","amount":165},{"name":"monkeyfarm","amount":156},{"name":"iJevin","amount":119},{"name":"Biffa2001","amount":102},{"name":"Spumwackles","amount":78},{"name":"hypnotizd","amount":57},{"name":"ZombieCleo","amount":53},{"name":"Etho","amount":44},{"name":"joehillssays","amount":42},{"name":"skyzm","amount":29},{"name":"PythonGB","amount":29},{"name":"Tinfoilchef","amount":27},{"name":"Docm77","amount":20},{"name":"Keralis1","amount":16},{"name":"NameOfSamuel","amount":16},{"name":"Pungence","amount":11},{"name":"Collen","amount":8}]